brainextractor/__init__.py
brainextractor/helpers.py
brainextractor/main.py
brainextractor/scripts/__init__.py
brainextractor/scripts/brainextractor.py
brainextractor/scripts/brainextractor_render.py
brainextractor-0.2.2.dist-info/LICENSE
brainextractor-0.2.2.dist-info/METADATA
brainextractor-0.2.2.dist-info/WHEEL
brainextractor-0.2.2.dist-info/entry_points.txt
brainextractor-0.2.2.dist-info/top_level.txt
brainextractor-0.2.2.dist-info/zip-safe
brainextractor-0.2.2.dist-info/RECORD
