Metadata-Version: 2.1
Name: brainextractor
Version: 0.2.2
Summary: brain extraction in python
Author-email: Andrew Van <vanandrew@wustl.edu>
License: MIT License
Project-URL: github, https://github.com/vanandrew/brainextractor
Keywords: python,image-processing,neuroscience,neuroimaging,segmentation,fsl,brain-extraction,skull-stripping
Classifier: License :: OSI Approved :: MIT License
Classifier: Programming Language :: Python :: 3
Classifier: Programming Language :: C++
Classifier: Topic :: Scientific/Engineering :: Image Processing
Requires-Python: >=3.7
License-File: LICENSE
Requires-Dist: numba (>=0.51.2)
Requires-Dist: nibabel (>=3.2.1)
Requires-Dist: trimesh (>=3.8.15)
Requires-Dist: numpy (>=1.19.4)
Requires-Dist: scipy (>=1.5.4)
Requires-Dist: pyrender (>=0.1.43)
Provides-Extra: dev
Requires-Dist: black (>=22.0) ; extra == 'dev'
